OpenConsoleGUILib/__init__.py
OpenConsoleGUILib/cgui.py
OpenConsoleGUILib-0.0.3.dist-info/METADATA
OpenConsoleGUILib-0.0.3.dist-info/WHEEL
OpenConsoleGUILib-0.0.3.dist-info/top_level.txt
OpenConsoleGUILib-0.0.3.dist-info/RECORD
