Metadata-Version: 2.1
Name: OpenConsoleGUILib
Version: 0.0.3
Summary: Create functional menus & loading bars in the terminal with just a few lines.
Author: SHARKstudio (Jay Morrington)
Author-email: <animating.du.38@gmail.com>
Keywords: python,menu,progress-bar,gui,terminal,console
Classifier: Intended Audience :: Developers
Classifier: Operating System :: Unix
Classifier: Operating System :: MacOS :: MacOS X
Classifier: Operating System :: Microsoft :: Windows
Requires-Dist: keyboard
